spacyrerank/__init__.py
spacyrerank/rerank.py
spacyrerank/spacy_pipeline.py
spacyrerank-0.0.6.dist-info/LICENSE
spacyrerank-0.0.6.dist-info/METADATA
spacyrerank-0.0.6.dist-info/WHEEL
spacyrerank-0.0.6.dist-info/top_level.txt
spacyrerank-0.0.6.dist-info/RECORD
