Metadata-Version: 2.1
Name: spacyrerank
Version: 0.0.6
Summary: Rank phrases and text based on query by leveraging hugging-face models.
Home-page: https://github.com/Vishnunkumar/spacyrerank
Author: Vishnu Nandakumar
Author-email: nkumarvishnu25@gmail.com
License: MIT license
Keywords: reranker,spacy,transformers
Classifier: Development Status :: 3 - Alpha
Classifier: Intended Audience :: Developers
Classifier: Topic :: Software Development :: Build Tools
Classifier: License :: OSI Approved :: MIT License
Classifier: Programming Language :: Python :: 3
Classifier: Programming Language :: Python :: 3.4
Classifier: Programming Language :: Python :: 3.5
Classifier: Programming Language :: Python :: 3.6
License-File: LICENSE
Requires-Dist: transformers
Requires-Dist: torch
Requires-Dist: spacy
